ensc/__init__.py
ensc/_modidx.py
ensc/cons.py
ensc/data.py
ensc/ensc.py
ensc/errs.py
ensc/reqs.py
ensc/util.py
ensc-0.0.4.dist-info/LICENSE
ensc-0.0.4.dist-info/METADATA
ensc-0.0.4.dist-info/WHEEL
ensc-0.0.4.dist-info/entry_points.txt
ensc-0.0.4.dist-info/top_level.txt
ensc-0.0.4.dist-info/RECORD
