Metadata-Version: 2.1
Name: ensc
Version: 0.0.4
Summary: ensc
Home-page: https://github.com/dsm-72/ensc
Author: dsm-72
Author-email: sumner.magruder@yale.edu
License: Apache Software License 2.0
Keywords: ensc phenotype cell biology ensembl client ens ensg
Classifier: Development Status :: 4 - Beta
Classifier: Intended Audience :: Developers
Classifier: Natural Language :: English
Classifier: Programming Language :: Python :: 3.11
Classifier: License :: OSI Approved :: Apache Software License
Requires-Python: >=3.11
License-File: LICENSE
Requires-Dist: nchr
Requires-Dist: nlit
Requires-Dist: pandas
Provides-Extra: dev
Requires-Dist: pandas ; extra == 'dev'
